apparate/__init__.py
apparate/_version.py
apparate/cli.py
apparate/cli_commands.py
apparate/configure.py
apparate/update_databricks_library.py
apparate-2.3.0.data/data/LICENSE.txt
apparate-2.3.0.dist-info/LICENSE.txt
apparate-2.3.0.dist-info/METADATA
apparate-2.3.0.dist-info/WHEEL
apparate-2.3.0.dist-info/entry_points.txt
apparate-2.3.0.dist-info/top_level.txt
apparate-2.3.0.dist-info/RECORD
