Metadata-Version: 2.1
Name: apparate
Version: 2.3.0
Summary: Update libraries on Databricks
Home-page: https://github.com/shoprunner/apparate
Author: Hanna Torrence
Author-email: htorrence@shoprunner.com
License: BSD-3-Clause
Platform: UNKNOWN
Requires-Dist: click
Requires-Dist: click-log
Requires-Dist: configparser
Requires-Dist: requests
Requires-Dist: simplejson
Provides-Extra: dev
Requires-Dist: flake8 ; extra == 'dev'
Requires-Dist: m2r ; extra == 'dev'
Requires-Dist: numpydoc ; extra == 'dev'
Requires-Dist: pytest ; extra == 'dev'
Requires-Dist: pytest-cov ; extra == 'dev'
Requires-Dist: responses ; extra == 'dev'
Requires-Dist: sphinx ; extra == 'dev'
Requires-Dist: sphinxcontrib-programoutput ; extra == 'dev'
